simpliroute/__init__.py
simpliroute/abstract/__init__.py
simpliroute/abstract/abstract_dataclass.py
simpliroute/config/__init__.py
simpliroute/config/config.py
simpliroute/items/__init__.py
simpliroute/items/item.py
simpliroute/properties/__init__.py
simpliroute/properties/properties.py
simpliroute/routes/__init__.py
simpliroute/routes/route.py
simpliroute/users/__init__.py
simpliroute/users/users.py
simpliroute/vehicles/__init__.py
simpliroute/vehicles/vehicle.py
simpliroute/visits/__init__.py
simpliroute/visits/visit.py
simpliroute/webhooks/__init__.py
simpliroute/webhooks/main.py
simpliroute/webhooks/webhook.py
simpliroute-1.0.4.1.dist-info/METADATA
simpliroute-1.0.4.1.dist-info/WHEEL
simpliroute-1.0.4.1.dist-info/RECORD
