Metadata-Version: 2.3
Name: simpliroute
Version: 1.0.4.1
Summary: Package to abstract simpliroute Rest api.
Author: Matias Rivera
Author-email: mrivera@chroma.agency
Requires-Python: >=3.7,<4.0
Classifier: Programming Language :: Python :: 3
Classifier: Programming Language :: Python :: 3.7
Classifier: Programming Language :: Python :: 3.8
Classifier: Programming Language :: Python :: 3.9
Classifier: Programming Language :: Python :: 3.10
Classifier: Programming Language :: Python :: 3.11
Classifier: Programming Language :: Python :: 3.12
Classifier: Programming Language :: Python :: 3.13
Requires-Dist: dataclasses-json (>=0.6.1,<0.7.0)
Requires-Dist: requests (>=2.31.0,<3.0.0)
